wsh/__init__.py
wsh/__main__.py
wsh/wshcopy.py
webssh_sh-22.11.8.dist-info/LICENSE
webssh_sh-22.11.8.dist-info/METADATA
webssh_sh-22.11.8.dist-info/WHEEL
webssh_sh-22.11.8.dist-info/entry_points.txt
webssh_sh-22.11.8.dist-info/top_level.txt
webssh_sh-22.11.8.dist-info/RECORD
