Metadata-Version: 2.1
Name: webssh-sh
Version: 22.11.8
Summary: Shell Helpers about WebSSH
Home-page: https://github.com/isontheline/webssh.sh
Author: Arnaud MENGUS
License: MIT
Classifier: License :: OSI Approved :: MIT License
Classifier: Programming Language :: Python :: 3
License-File: LICENSE
